{"id": "5mnW1gdGSbM", "title": "Helga Zepp-LaRouche - Discours d’ouverture : Rebâtir le monde à l’ère des BRICS", "duration": 3691, "upload_date": "20150619", "description": "Helga Zepp-LaRouche, présidente de l'Institut Schiller.\nREBÂTIR LE MONDE À L'ÈRE DES BRICS\nConférence internationale de l'Institut Schiller\nParis, les 13 et 14 juin 2015\nhttp://newparadigm.schillerinstitute.com/fr", "chapters": [{"start_time": 0, "title": "Introduction", "end_time": 12}, {"start_time": 12, "title": "Préface", "end_time": 353}, {"start_time": 353, "title": "Le pont terrestre eurasiatique", "end_time": 581}, {"start_time": 581, "title": "La réduction de la population mondiale", "end_time": 783}, {"start_time": 783, "title": "L’hégémonie anglo-américaine", "end_time": 898}, {"start_time": 898, "title": "L’hégémonie russe", "end_time": 1073}, {"start_time": 1073, "title": "Exercices militaires", "end_time": 1138}, {"start_time": 1138, "title": "Ukraine", "end_time": 1273}, {"start_time": 1273, "title": "Exportations allemandes", "end_time": 1373}, {"start_time": 1373, "title": "Décarbonation de l’économie", "end_time": 1863}, {"start_time": 1863, "title": "Nouveau système financier mondial", "end_time": 2053}, {"start_time": 2053, "title": "Nouveau partenariat stratégique", "end_time": 2188}, {"start_time": 2188, "title": "Nouvelle route de la soie", "end_time": 2263}, {"start_time": 2263, "title": "L’union soviétique s’effondre", "end_time": 2448}, {"start_time": 2448, "title": "La nouvelle route de la soie", "end_time": 2553}, {"start_time": 2553, "title": "L’image de la Chine", "end_time": 2698}, {"start_time": 2698, "title": "L’harmonie sans uniformité", "end_time": 2758}, {"start_time": 2758, "title": "L’harmonie dans son ménage", "end_time": 2803}, {"start_time": 2803, "title": "L’harmonie dans une société", "end_time": 2983}, {"start_time": 2983, "title": "Le beau, le bon et le vrai", "end_time": 3263}, {"start_time": 3263, "title": "Conclusion", "end_time": 3691}], "playlists": ["PLoHwt4KyUk5AlUKhGlU7z1dqj9XBCPtHa"], "automatic_captions": ["aa", "ab", "af", "ak", "am", "ar"]}