{"id": "cy0uh-BYs7s", "title": "Panel 3: “Creativity as the Distinctive Characteristic of Human Culture", "duration": 12606, "upload_date": "20200426", "description": "Conference webpage: https://schillerinstitute.com/blog/2020/03/29/conference-mankinds-existence-now-depends-on-the-establishment-of-a-new-paradigm/\n\nPanel Moderators: Kesha Rogers and Dennis Speed, the following times are U.S. EDT\n\n11:00-11:15 — Beethoven, “An die ferne Geliebte,” op. 98\nJohn Sigerson, tenor, Margaret Greenspan, piano \n\n11:15 — Lyndon LaRouche\n“I Have Insisted That Music Is Intelligible!” \n\n11:20 — Helga Zepp-LaRouche\nFounder and Chairman, Schiller Institute \n\n11:40 — William Warfield\n“A Poetic Musical Offering” \n\n11:45 — Willis Patterson\nBass-baritone, professor emeritus / Associate Dean of the University of Michigan School of Music, Theatre & Dance\n“The Presence of the Classical Principle in Folk Music” \n\n12:10 — John Sigerson\nMusic Director for the Schiller Institute, co-author of A Manual on the Rudiments of Tuning and Registration\n“The Physical Power of Classical Poetry and Music” \n\n12:30 — Eugene Simpson\nProfessor emeritus of Voice and Choral Literature, Rowan University of New Jersey; Founding Curator of the Hall Johnson Collection\n“Hall Johnson and the Dvorak Dream: From Spiritual to Art Song” \n\n1:00 — Diane Sare\nFounder and co-director, Schiller Institute NYC Chorus\n“On the Employment of Chorus in Politics” \n\n1:25 — Conference Greetings, Gregory Hopkins\nFounder and Artistic Director, Harlem Opera Theater. \n\n1:30–2:15 — Discussion and Q&A\n\nLudwig van Beethoven: “An die ferne Geliebte,” Op. 98 Poem by Ludwig Rellstab (1799–1860)\n Original German:\n https://www.lieder.net/lieder/assemble_texts.html?SongCycleId=128 \n\nEnglish:  https://www.lieder.net/lieder/assemble_translations.html?LanguageId=7&SongCycleId=128&ContribId=251 \n\nFrench:\n https://www.lieder.net/lieder/assemble_translations.html?LanguageId=10&SongCycleId=128&ContribId=440 \n\nItalian:\n https://www.lieder.net/lieder/assemble_translations.html?LanguageId=16&SongCycleId=128&ContribId=472 \n\nSpanish:\n https://www.lieder.net/lieder/assemble_translations.html?LanguageId=26&SongCycleId=128&ContribId=832 \n\nChinese:\n https://baike.baidu.com/item/致远方的爱人/4344271?fr=aladdin \n\nThe decadence that has entered much of the culture of the Western world is itself a sign of the end of the system. The cult of ugliness is dominating much of what counts as art today. Meaningless violence and perversion in the so-called entertainment industry play a role in shaping a popular culture in which mass shootings, drug addiction, and cultural pessimism are prevalent. \n\nThe replacement of the Dark Age of the 14th century, described in literature by Boccaccio and in paintings by Bruegel and Bosch, with the cultural optimism and new image of man of the Golden Renaissance in Italy and other parts of Europe, is a good example that human ingenuity can overcome terrible crises and replace them with new ideas and works of great art.\n\nToday a revival of classical art is the indispensable precondition for mankind to open a new chapter in human history. A renaissance of classical music, and a dialogue of the best classical traditions of all cultures, must lay the foundation for a new renaissance. Works such as those of Dante, Leonardo da Vinci, Bach, Mozart, Beethoven, Verdi, Du Fu, Shakespeare, Schiller, Tagore, Huang Gongwang, Rembrandt, Goya, Cervantes, Rabelais, and Pushkin, just to name a few, embody principles which inspire the creativity of the human mind and are as universal as principles of physical science. The knowledge of these arts is the basis for the aesthetic education of man. As Lyndon LaRouche wrote beautifully, the essence of great art is love. In this Year of Beethoven, we absolutely can gain the inner strength to master this crisis by evoking his spirit and by thinking like the great composer.", "chapters": [{"start_time": 0, "end_time": 1692, "title": "<Untitled Chapter 1>"}, {"start_time": 1692, "title": "Friedrich Schiller, Aesthetical Letters", "end_time": 1868}, {"start_time": 1868, "title": "Friedrich Schiller, Theosophy of Julius", "end_time": 2861}, {"start_time": 2861, "title": "Largo - Dvorak New World Symphony", "end_time": 3322}, {"start_time": 3322, "title": "Ride On, King Jesus, Hall Johnson", "end_time": 3564}, {"start_time": 3564, "title": "Am Meer. FRANZ SCHUBERT.", "end_time": 12606}], "playlists": ["PLoHwt4KyUk5BLyjo-lYI1akY_m95R12QD"], "automatic_captions": ["aa", "ab", "af", "ak", "am", "ar"]}