{"id": "gRmsxFnAVUM", "title": "Webcast: The BRICS Summit and the End to 500 Years of Colonialism", "duration": 2640, "upload_date": "20241031", "description": "Join Helga Zepp-#LaRouche October 30, 11am Eastern/4pm CET in her Weekly Live dialogue and help usher in the Year of the New Paradigm for all Humanity. Send your questions, thoughts and reports to questions@schillerinstitute.org or ask them in the live stream.\n\n#Ukraine #Russia #China #Nato #Palestine #brics #Israel #War #nuclearwar #cruisemissile #taurus #MLK #BRI #trump #Biden \n\nIn a Monday meeting, Oct. 28, held to evaluate the history-making events of last week—including the Oct. 22-24 Kazan, Russia BRICS summit; the Oct. 26 symposium/concert “Build a Chorus of Peace Against the Ghouls of War,” hosted by LaRouche Independent candidates Diane Sare and Jose Vega; and the Sunday, Oct. 27 “Operation DAWN, Threat of Nuclear War in the World Today” brunch, organized by former U.S. Marines intelligence officer and whistleblower Scott Ritter—Schiller Institute head Helga Zepp-LaRouche, both contributor to and participant in those events, and earlier processes that made the achievements of those events possible, indicated what she believed needed to happen next. “We have to absolutely make clear that the only way how the danger of a Third World War can be overcome, is that we have to get the collective West—that’s the United States and the European nations—to stop their silly geopolitical confrontation against this new majority of the world. After all, the BRICS (Brazil, Russia, India, China, South Africa, plus other nations) as they are now, represents 4.7 billion people, and 57% of the world’s population, and there are many more countries in line waiting to join. And it would be foolish, to the point of insanity, if the West would continue to oppose that.”\n\nAn international audience heard former American military officers of high rank, journalists, and even comedians, in dialogue among themselves, and with Helga Zepp-LaRouche. “These nations of the Global South are already the Global Majority, and they are determined to end the period of 500 years of colonialism, by building a new world economic system which will allow them to industrialize and overcome poverty and underdevelopment,” she said to the Saturday symposium. “They are building a great, New Development Bank of the Global South, a new Investment platform, a new BRICS grain exchange, and other institutions, which will help them to grow. It is the most urgent task for reestablishing world peace that the United States supports this effort. We must remember that the American War of Independence was the first anti-colonial war in history, by establishing independence of America from the British Empire.”\n\nThe Ten Principles for a New International Strategic and Development Architecture by Helga Zepp-LaRouche are not only a statement of principle, but a statement of intent, which, if adopted by people in the trans-Atlantic world, would supply the only means by which a collaboration with the nations of the Global South, and the Global Majority would ever be trusted, and therefore realized.\n\nBuild a Chorus of Peace Against the Ghouls of War: https://www.youtube.com/watch?v=QV7-5_gRv_U\nTen Principles for a New International Strategic and Development Architecture: https://schillerinstitute.com/blog/2022/11/30/ten-principles-of-a-new-international-security-and-development-architecture/\nGet your daily news here: https://eir.news/", "chapters": null, "playlists": ["PLoHwt4KyUk5ABVrLKbPsc2NTJagRbMN1I"], "automatic_captions": ["aa", "ab", "af", "ak", "am", "ar"]}