{"id": "XAsObmq-5X0", "title": "Leonidas Chrysantopoulos – La crise globale, des propositions pour s’en sortir", "duration": 1249, "upload_date": "20160705", "description": "Leonidas Chrysantopoulos – ancien ambassadeur grec en Pologne, au Canada et en Arménie, ancien secrétaire général de l’Organisation de coopération économique de la mer Noire (BSEC)\n\nDiscours prononcé à la conférence internationale de l'Institut Schiller à Berlin, les 25 et 26 juin 2016.\n\nProgramme complet, vidéos et texte sont disponibles sur cette page : \nhttp://newparadigm.schillerinstitute.com/fr/conference-berlin-2016-june-25-26/\n\nRejoignez la bataille !\nhttp://newparadigm.schillerinstitute.com/fr/rejoindre/", "chapters": [{"start_time": 0, "title": "Introduction", "end_time": 142}, {"start_time": 142, "title": "L’UE dans le désarroi", "end_time": 500}, {"start_time": 500, "title": "La dette grecque", "end_time": 780}, {"start_time": 780, "title": "L’animosité américaine envers la Russie", "end_time": 852}, {"start_time": 852, "title": "Les propositions de la Chine", "end_time": 885}, {"start_time": 885, "title": "Les propositions de la Grèce", "end_time": 924}, {"start_time": 924, "title": "Le dialogue des cultures", "end_time": 977}, {"start_time": 977, "title": "La cessation des paiements", "end_time": 1047}, {"start_time": 1047, "title": "Les propositions pour s’en sortir", "end_time": 1249}], "playlists": ["PLoHwt4KyUk5BoCPR6750Eh-_mxhkzQVrF"], "automatic_captions": ["aa", "ab", "af", "ak", "am", "ar"]}