{"id": "ZzCHkgfY7Ow", "title": "There Must Be a Clear Voice to Counter the War Hawks: Discuss Helga Zepp-LaRouche", "duration": 2240, "upload_date": "20230504", "description": "We need everyone to muster their courage and intervene across the world! Have a discussion with Helga Zepp-LaRouche! Go through the world historic situation and what we can do to intervene on it. \n\nEmail in your questions, thoughts and organizing reports to \nquestions@schillerinstitute.org \nor join us live and post them in the YouTube chat.\n\nWe look forward to hearing from you!\nHave fun.", "chapters": null, "playlists": ["PLoHwt4KyUk5ABVrLKbPsc2NTJagRbMN1I"], "automatic_captions": ["aa", "ab", "af", "ak", "am", "ar"]}